<?xml version="1.0" encoding="utf-8" ?>
<dwsync>
<file name=".DS_Store" server="ftp.bennettcodes.com" local="130918025972724496" remote="130917642000000000" Dst="1" />
<file name="hotel-information-sheet.pdf" server="ftp.bennettcodes.com" local="130918026013517386" remote="130917642600000000" Dst="1" />
<file name="index.php" server="ftp.bennettcodes.com" local="130918026101765007" remote="130917642600000000" Dst="1" />
<file name="thankyou.php" server="ftp.bennettcodes.com" local="130918026528702611" remote="130917643800000000" Dst="1" />
<file name=".DS_Store" server="ftp.bennettcodes.com//" local="130918025972724496" remote="130957518000000000" Dst="1" />
<file name="hotel-information-sheet.pdf" server="ftp.bennettcodes.com//" local="130918026013517386" remote="130957518000000000" Dst="1" />
<file name="index.php" server="ftp.bennettcodes.com//" local="130918026101765007" remote="130957518000000000" Dst="1" />
<file name="thankyou.php" server="ftp.bennettcodes.com//" local="130918026528702611" remote="130957518600000000" Dst="1" />
</dwsync>